<?xml version="1.0"?>
<graph name="G" nb_arcs="643" nb_vertices="130" nb_niveaux="12" density="0.5">;
 <vertex name="v90"/>
 <vertex name="v39"/>
 <vertex name="v81"/>
 <vertex name="v05"/>
 <vertex name="v72"/>
 <vertex name="v127"/>
 <vertex name="v30"/>
 <vertex name="v86"/>
 <vertex name="v84"/>
 <vertex name="v25"/>
 <vertex name="v82"/>
 <vertex name="v54"/>
 <vertex name="v48"/>
 <vertex name="v42"/>
 <vertex name="v66"/>
 <vertex name="v58"/>
 <vertex name="v37"/>
 <vertex name="v106"/>
 <vertex name="v93"/>
 <vertex name="v03"/>
 <vertex name="v67"/>
 <vertex name="v13"/>
 <vertex name="v123"/>
 <vertex name="v59"/>
 <vertex name="v18"/>
 <vertex name="v52"/>
 <vertex name="v20"/>
 <vertex name="v101"/>
 <vertex name="v14"/>
 <vertex name="v16"/>
 <vertex name="v41"/>
 <vertex name="v114"/>
 <vertex name="v44"/>
 <vertex name="v69"/>
 <vertex name="v55"/>
 <vertex name="v99"/>
 <vertex name="v91"/>
 <vertex name="v32"/>
 <vertex name="v97"/>
 <vertex name="v95"/>
 <vertex name="v75"/>
 <vertex name="v29"/>
 <vertex name="v77"/>
 <vertex name="v60"/>
 <vertex name="v38"/>
 <vertex name="v36"/>
 <vertex name="v129"/>
 <vertex name="v102"/>
 <vertex name="v111"/>
 <vertex name="v105"/>
 <vertex name="v24"/>
 <vertex name="v73"/>
 <vertex name="v09"/>
 <vertex name="v79"/>
 <vertex name="v109"/>
 <vertex name="v35"/>
 <vertex name="v113"/>
 <vertex name="v85"/>
 <vertex name="v12"/>
 <vertex name="v34"/>
 <vertex name="v116"/>
 <vertex name="v07"/>
 <vertex name="v17"/>
 <vertex name="v46"/>
 <vertex name="v43"/>
 <vertex name="v87"/>
 <vertex name="v06"/>
 <vertex name="v107"/>
 <vertex name="v71"/>
 <vertex name="v26"/>
 <vertex name="v124"/>
 <vertex name="v117"/>
 <vertex name="v57"/>
 <vertex name="v115"/>
 <vertex name="v61"/>
 <vertex name="v122"/>
 <vertex name="v02"/>
 <vertex name="v21"/>
 <vertex name="v118"/>
 <vertex name="v128"/>
 <vertex name="v51"/>
 <vertex name="v49"/>
 <vertex name="v78"/>
 <vertex name="v94"/>
 <vertex name="v110"/>
 <vertex name="v120"/>
 <vertex name="v00"/>
 <vertex name="v80"/>
 <vertex name="v65"/>
 <vertex name="v98"/>
 <vertex name="v89"/>
 <vertex name="v23"/>
 <vertex name="v53"/>
 <vertex name="v10"/>
 <vertex name="v45"/>
 <vertex name="v83"/>
 <vertex name="v63"/>
 <vertex name="v19"/>
 <vertex name="v56"/>
 <vertex name="v125"/>
 <vertex name="v28"/>
 <vertex name="v22"/>
 <vertex name="v108"/>
 <vertex name="v119"/>
 <vertex name="v96"/>
 <vertex name="v74"/>
 <vertex name="v100"/>
 <vertex name="v50"/>
 <vertex name="v121"/>
 <vertex name="v15"/>
 <vertex name="v104"/>
 <vertex name="v92"/>
 <vertex name="v64"/>
 <vertex name="v31"/>
 <vertex name="v04"/>
 <vertex name="v70"/>
 <vertex name="v88"/>
 <vertex name="v62"/>
 <vertex name="v11"/>
 <vertex name="v47"/>
 <vertex name="v08"/>
 <vertex name="v01"/>
 <vertex name="v68"/>
 <vertex name="v112"/>
 <vertex name="v40"/>
 <vertex name="v33"/>
 <vertex name="v76"/>
 <vertex name="v126"/>
 <vertex name="v103"/>
 <vertex name="v27"/>
 <arc name="v00->v14" from="v00" to="v14"/>
 <arc name="v01->v15" from="v01" to="v15"/>
 <arc name="v02->v16" from="v02" to="v16"/>
 <arc name="v03->v17" from="v03" to="v17"/>
 <arc name="v04->v18" from="v04" to="v18"/>
 <arc name="v05->v19" from="v05" to="v19"/>
 <arc name="v06->v20" from="v06" to="v20"/>
 <arc name="v07->v21" from="v07" to="v21"/>
 <arc name="v08->v22" from="v08" to="v22"/>
 <arc name="v09->v23" from="v09" to="v23"/>
 <arc name="v10->v24" from="v10" to="v24"/>
 <arc name="v11->v25" from="v11" to="v25"/>
 <arc name="v12->v26" from="v12" to="v26"/>
 <arc name="v13->v27" from="v13" to="v27"/>
 <arc name="v14->v28" from="v14" to="v28"/>
 <arc name="v15->v28" from="v15" to="v28"/>
 <arc name="v16->v29" from="v16" to="v29"/>
 <arc name="v17->v30" from="v17" to="v30"/>
 <arc name="v18->v31" from="v18" to="v31"/>
 <arc name="v19->v32" from="v19" to="v32"/>
 <arc name="v20->v33" from="v20" to="v33"/>
 <arc name="v21->v34" from="v21" to="v34"/>
 <arc name="v22->v35" from="v22" to="v35"/>
 <arc name="v23->v36" from="v23" to="v36"/>
 <arc name="v24->v37" from="v24" to="v37"/>
 <arc name="v25->v38" from="v25" to="v38"/>
 <arc name="v26->v39" from="v26" to="v39"/>
 <arc name="v27->v40" from="v27" to="v40"/>
 <arc name="v28->v41" from="v28" to="v41"/>
 <arc name="v29->v41" from="v29" to="v41"/>
 <arc name="v30->v42" from="v30" to="v42"/>
 <arc name="v31->v43" from="v31" to="v43"/>
 <arc name="v32->v44" from="v32" to="v44"/>
 <arc name="v33->v44" from="v33" to="v44"/>
 <arc name="v34->v45" from="v34" to="v45"/>
 <arc name="v35->v46" from="v35" to="v46"/>
 <arc name="v36->v47" from="v36" to="v47"/>
 <arc name="v37->v47" from="v37" to="v47"/>
 <arc name="v38->v48" from="v38" to="v48"/>
 <arc name="v39->v49" from="v39" to="v49"/>
 <arc name="v40->v50" from="v40" to="v50"/>
 <arc name="v41->v51" from="v41" to="v51"/>
 <arc name="v41->v52" from="v41" to="v52"/>
 <arc name="v42->v53" from="v42" to="v53"/>
 <arc name="v43->v54" from="v43" to="v54"/>
 <arc name="v44->v55" from="v44" to="v55"/>
 <arc name="v44->v56" from="v44" to="v56"/>
 <arc name="v45->v57" from="v45" to="v57"/>
 <arc name="v46->v58" from="v46" to="v58"/>
 <arc name="v47->v59" from="v47" to="v59"/>
 <arc name="v47->v60" from="v47" to="v60"/>
 <arc name="v48->v61" from="v48" to="v61"/>
 <arc name="v49->v62" from="v49" to="v62"/>
 <arc name="v50->v63" from="v50" to="v63"/>
 <arc name="v51->v64" from="v51" to="v64"/>
 <arc name="v52->v64" from="v52" to="v64"/>
 <arc name="v53->v65" from="v53" to="v65"/>
 <arc name="v54->v66" from="v54" to="v66"/>
 <arc name="v55->v67" from="v55" to="v67"/>
 <arc name="v56->v68" from="v56" to="v68"/>
 <arc name="v57->v69" from="v57" to="v69"/>
 <arc name="v58->v70" from="v58" to="v70"/>
 <arc name="v59->v71" from="v59" to="v71"/>
 <arc name="v60->v72" from="v60" to="v72"/>
 <arc name="v61->v73" from="v61" to="v73"/>
 <arc name="v62->v74" from="v62" to="v74"/>
 <arc name="v63->v75" from="v63" to="v75"/>
 <arc name="v64->v76" from="v64" to="v76"/>
 <arc name="v65->v76" from="v65" to="v76"/>
 <arc name="v66->v76" from="v66" to="v76"/>
 <arc name="v67->v77" from="v67" to="v77"/>
 <arc name="v68->v77" from="v68" to="v77"/>
 <arc name="v69->v78" from="v69" to="v78"/>
 <arc name="v70->v78" from="v70" to="v78"/>
 <arc name="v71->v78" from="v71" to="v78"/>
 <arc name="v72->v79" from="v72" to="v79"/>
 <arc name="v73->v79" from="v73" to="v79"/>
 <arc name="v74->v80" from="v74" to="v80"/>
 <arc name="v75->v80" from="v75" to="v80"/>
 <arc name="v76->v81" from="v76" to="v81"/>
 <arc name="v76->v82" from="v76" to="v82"/>
 <arc name="v76->v83" from="v76" to="v83"/>
 <arc name="v77->v84" from="v77" to="v84"/>
 <arc name="v77->v85" from="v77" to="v85"/>
 <arc name="v77->v86" from="v77" to="v86"/>
 <arc name="v78->v87" from="v78" to="v87"/>
 <arc name="v78->v88" from="v78" to="v88"/>
 <arc name="v79->v89" from="v79" to="v89"/>
 <arc name="v79->v90" from="v79" to="v90"/>
 <arc name="v79->v91" from="v79" to="v91"/>
 <arc name="v80->v92" from="v80" to="v92"/>
 <arc name="v80->v93" from="v80" to="v93"/>
 <arc name="v81->v94" from="v81" to="v94"/>
 <arc name="v82->v95" from="v82" to="v95"/>
 <arc name="v83->v96" from="v83" to="v96"/>
 <arc name="v84->v97" from="v84" to="v97"/>
 <arc name="v85->v98" from="v85" to="v98"/>
 <arc name="v86->v99" from="v86" to="v99"/>
 <arc name="v87->v100" from="v87" to="v100"/>
 <arc name="v88->v101" from="v88" to="v101"/>
 <arc name="v89->v102" from="v89" to="v102"/>
 <arc name="v90->v103" from="v90" to="v103"/>
 <arc name="v91->v104" from="v91" to="v104"/>
 <arc name="v92->v105" from="v92" to="v105"/>
 <arc name="v93->v106" from="v93" to="v106"/>
 <arc name="v94->v107" from="v94" to="v107"/>
 <arc name="v95->v107" from="v95" to="v107"/>
 <arc name="v96->v107" from="v96" to="v107"/>
 <arc name="v97->v108" from="v97" to="v108"/>
 <arc name="v98->v108" from="v98" to="v108"/>
 <arc name="v99->v109" from="v99" to="v109"/>
 <arc name="v100->v109" from="v100" to="v109"/>
 <arc name="v101->v110" from="v101" to="v110"/>
 <arc name="v102->v110" from="v102" to="v110"/>
 <arc name="v103->v111" from="v103" to="v111"/>
 <arc name="v104->v111" from="v104" to="v111"/>
 <arc name="v105->v112" from="v105" to="v112"/>
 <arc name="v106->v112" from="v106" to="v112"/>
 <arc name="v107->v113" from="v107" to="v113"/>
 <arc name="v107->v114" from="v107" to="v114"/>
 <arc name="v108->v115" from="v108" to="v115"/>
 <arc name="v109->v116" from="v109" to="v116"/>
 <arc name="v110->v117" from="v110" to="v117"/>
 <arc name="v110->v118" from="v110" to="v118"/>
 <arc name="v111->v119" from="v111" to="v119"/>
 <arc name="v112->v120" from="v112" to="v120"/>
 <arc name="v113->v121" from="v113" to="v121"/>
 <arc name="v113->v122" from="v113" to="v122"/>
 <arc name="v114->v123" from="v114" to="v123"/>
 <arc name="v115->v124" from="v115" to="v124"/>
 <arc name="v116->v125" from="v116" to="v125"/>
 <arc name="v117->v126" from="v117" to="v126"/>
 <arc name="v118->v127" from="v118" to="v127"/>
 <arc name="v119->v128" from="v119" to="v128"/>
 <arc name="v120->v129" from="v120" to="v129"/>
 <arc name="v41->v62" from="v41" to="v62"/>
 <arc name="v29->v47" from="v29" to="v47"/>
 <arc name="v111->v118" from="v111" to="v118"/>
 <arc name="v76->v91" from="v76" to="v91"/>
 <arc name="v08->v15" from="v08" to="v15"/>
 <arc name="v91->v105" from="v91" to="v105"/>
 <arc name="v78->v83" from="v78" to="v83"/>
 <arc name="v106->v109" from="v106" to="v109"/>
 <arc name="v79->v93" from="v79" to="v93"/>
 <arc name="v34->v43" from="v34" to="v43"/>
 <arc name="v120->v124" from="v120" to="v124"/>
 <arc name="v115->v122" from="v115" to="v122"/>
 <arc name="v49->v55" from="v49" to="v55"/>
 <arc name="v66->v80" from="v66" to="v80"/>
 <arc name="v103->v109" from="v103" to="v109"/>
 <arc name="v115->v129" from="v115" to="v129"/>
 <arc name="v24->v33" from="v24" to="v33"/>
 <arc name="v50->v62" from="v50" to="v62"/>
 <arc name="v34->v46" from="v34" to="v46"/>
 <arc name="v68->v78" from="v68" to="v78"/>
 <arc name="v29->v48" from="v29" to="v48"/>
 <arc name="v97->v110" from="v97" to="v110"/>
 <arc name="v19->v40" from="v19" to="v40"/>
 <arc name="v69->v79" from="v69" to="v79"/>
 <arc name="v114->v129" from="v114" to="v129"/>
 <arc name="v108->v116" from="v108" to="v116"/>
 <arc name="v107->v115" from="v107" to="v115"/>
 <arc name="v45->v52" from="v45" to="v52"/>
 <arc name="v68->v79" from="v68" to="v79"/>
 <arc name="v116->v128" from="v116" to="v128"/>
 <arc name="v60->v69" from="v60" to="v69"/>
 <arc name="v57->v71" from="v57" to="v71"/>
 <arc name="v97->v111" from="v97" to="v111"/>
 <arc name="v05->v22" from="v05" to="v22"/>
 <arc name="v47->v55" from="v47" to="v55"/>
 <arc name="v29->v42" from="v29" to="v42"/>
 <arc name="v18->v28" from="v18" to="v28"/>
 <arc name="v92->v100" from="v92" to="v100"/>
 <arc name="v22->v28" from="v22" to="v28"/>
 <arc name="v114->v121" from="v114" to="v121"/>
 <arc name="v37->v46" from="v37" to="v46"/>
 <arc name="v98->v107" from="v98" to="v107"/>
 <arc name="v93->v102" from="v93" to="v102"/>
 <arc name="v78->v85" from="v78" to="v85"/>
 <arc name="v113->v129" from="v113" to="v129"/>
 <arc name="v88->v105" from="v88" to="v105"/>
 <arc name="v58->v66" from="v58" to="v66"/>
 <arc name="v05->v16" from="v05" to="v16"/>
 <arc name="v109->v120" from="v109" to="v120"/>
 <arc name="v07->v18" from="v07" to="v18"/>
 <arc name="v77->v92" from="v77" to="v92"/>
 <arc name="v109->v118" from="v109" to="v118"/>
 <arc name="v33->v43" from="v33" to="v43"/>
 <arc name="v44->v54" from="v44" to="v54"/>
 <arc name="v20->v40" from="v20" to="v40"/>
 <arc name="v17->v33" from="v17" to="v33"/>
 <arc name="v62->v68" from="v62" to="v68"/>
 <arc name="v55->v64" from="v55" to="v64"/>
 <arc name="v05->v17" from="v05" to="v17"/>
 <arc name="v112->v114" from="v112" to="v114"/>
 <arc name="v73->v80" from="v73" to="v80"/>
 <arc name="v44->v61" from="v44" to="v61"/>
 <arc name="v33->v41" from="v33" to="v41"/>
 <arc name="v93->v98" from="v93" to="v98"/>
 <arc name="v99->v110" from="v99" to="v110"/>
 <arc name="v76->v87" from="v76" to="v87"/>
 <arc name="v111->v113" from="v111" to="v113"/>
 <arc name="v35->v45" from="v35" to="v45"/>
 <arc name="v91->v96" from="v91" to="v96"/>
 <arc name="v22->v38" from="v22" to="v38"/>
 <arc name="v58->v71" from="v58" to="v71"/>
 <arc name="v116->v127" from="v116" to="v127"/>
 <arc name="v109->v114" from="v109" to="v114"/>
 <arc name="v93->v105" from="v93" to="v105"/>
 <arc name="v115->v125" from="v115" to="v125"/>
 <arc name="v69->v77" from="v69" to="v77"/>
 <arc name="v80->v85" from="v80" to="v85"/>
 <arc name="v87->v98" from="v87" to="v98"/>
 <arc name="v98->v110" from="v98" to="v110"/>
 <arc name="v43->v51" from="v43" to="v51"/>
 <arc name="v115->v126" from="v115" to="v126"/>
 <arc name="v108->v117" from="v108" to="v117"/>
 <arc name="v00->v19" from="v00" to="v19"/>
 <arc name="v45->v59" from="v45" to="v59"/>
 <arc name="v09->v20" from="v09" to="v20"/>
 <arc name="v120->v127" from="v120" to="v127"/>
 <arc name="v74->v77" from="v74" to="v77"/>
 <arc name="v45->v51" from="v45" to="v51"/>
 <arc name="v79->v83" from="v79" to="v83"/>
 <arc name="v09->v26" from="v09" to="v26"/>
 <arc name="v30->v43" from="v30" to="v43"/>
 <arc name="v28->v47" from="v28" to="v47"/>
 <arc name="v40->v43" from="v40" to="v43"/>
 <arc name="v52->v72" from="v52" to="v72"/>
 <arc name="v110->v120" from="v110" to="v120"/>
 <arc name="v38->v49" from="v38" to="v49"/>
 <arc name="v39->v45" from="v39" to="v45"/>
 <arc name="v04->v26" from="v04" to="v26"/>
 <arc name="v109->v119" from="v109" to="v119"/>
 <arc name="v54->v64" from="v54" to="v64"/>
 <arc name="v98->v111" from="v98" to="v111"/>
 <arc name="v83->v94" from="v83" to="v94"/>
 <arc name="v34->v47" from="v34" to="v47"/>
 <arc name="v103->v110" from="v103" to="v110"/>
 <arc name="v37->v49" from="v37" to="v49"/>
 <arc name="v96->v111" from="v96" to="v111"/>
 <arc name="v09->v18" from="v09" to="v18"/>
 <arc name="v119->v122" from="v119" to="v122"/>
 <arc name="v43->v63" from="v43" to="v63"/>
 <arc name="v11->v19" from="v11" to="v19"/>
 <arc name="v10->v20" from="v10" to="v20"/>
 <arc name="v52->v67" from="v52" to="v67"/>
 <arc name="v47->v63" from="v47" to="v63"/>
 <arc name="v77->v88" from="v77" to="v88"/>
 <arc name="v11->v21" from="v11" to="v21"/>
 <arc name="v30->v45" from="v30" to="v45"/>
 <arc name="v88->v102" from="v88" to="v102"/>
 <arc name="v107->v118" from="v107" to="v118"/>
 <arc name="v17->v31" from="v17" to="v31"/>
 <arc name="v50->v51" from="v50" to="v51"/>
 <arc name="v53->v73" from="v53" to="v73"/>
 <arc name="v51->v72" from="v51" to="v72"/>
 <arc name="v92->v95" from="v92" to="v95"/>
 <arc name="v84->v104" from="v84" to="v104"/>
 <arc name="v12->v22" from="v12" to="v22"/>
 <arc name="v107->v117" from="v107" to="v117"/>
 <arc name="v21->v28" from="v21" to="v28"/>
 <arc name="v76->v89" from="v76" to="v89"/>
 <arc name="v80->v87" from="v80" to="v87"/>
 <arc name="v35->v41" from="v35" to="v41"/>
 <arc name="v59->v70" from="v59" to="v70"/>
 <arc name="v93->v103" from="v93" to="v103"/>
 <arc name="v112->v118" from="v112" to="v118"/>
 <arc name="v48->v63" from="v48" to="v63"/>
 <arc name="v28->v50" from="v28" to="v50"/>
 <arc name="v33->v45" from="v33" to="v45"/>
 <arc name="v13->v25" from="v13" to="v25"/>
 <arc name="v103->v107" from="v103" to="v107"/>
 <arc name="v85->v95" from="v85" to="v95"/>
 <arc name="v28->v46" from="v28" to="v46"/>
 <arc name="v77->v81" from="v77" to="v81"/>
 <arc name="v10->v22" from="v10" to="v22"/>
 <arc name="v43->v56" from="v43" to="v56"/>
 <arc name="v23->v29" from="v23" to="v29"/>
 <arc name="v24->v30" from="v24" to="v30"/>
 <arc name="v79->v92" from="v79" to="v92"/>
 <arc name="v72->v76" from="v72" to="v76"/>
 <arc name="v117->v123" from="v117" to="v123"/>
 <arc name="v116->v122" from="v116" to="v122"/>
 <arc name="v48->v57" from="v48" to="v57"/>
 <arc name="v52->v75" from="v52" to="v75"/>
 <arc name="v04->v20" from="v04" to="v20"/>
 <arc name="v84->v95" from="v84" to="v95"/>
 <arc name="v20->v30" from="v20" to="v30"/>
 <arc name="v90->v101" from="v90" to="v101"/>
 <arc name="v52->v71" from="v52" to="v71"/>
 <arc name="v71->v79" from="v71" to="v79"/>
 <arc name="v119->v124" from="v119" to="v124"/>
 <arc name="v75->v79" from="v75" to="v79"/>
 <arc name="v76->v84" from="v76" to="v84"/>
 <arc name="v67->v76" from="v67" to="v76"/>
 <arc name="v64->v80" from="v64" to="v80"/>
 <arc name="v77->v91" from="v77" to="v91"/>
 <arc name="v108->v118" from="v108" to="v118"/>
 <arc name="v54->v74" from="v54" to="v74"/>
 <arc name="v90->v95" from="v90" to="v95"/>
 <arc name="v112->v119" from="v112" to="v119"/>
 <arc name="v118->v121" from="v118" to="v121"/>
 <arc name="v46->v53" from="v46" to="v53"/>
 <arc name="v86->v95" from="v86" to="v95"/>
 <arc name="v69->v80" from="v69" to="v80"/>
 <arc name="v37->v48" from="v37" to="v48"/>
 <arc name="v113->v127" from="v113" to="v127"/>
 <arc name="v108->v113" from="v108" to="v113"/>
 <arc name="v112->v117" from="v112" to="v117"/>
 <arc name="v61->v64" from="v61" to="v64"/>
 <arc name="v112->v115" from="v112" to="v115"/>
 <arc name="v36->v44" from="v36" to="v44"/>
 <arc name="v97->v112" from="v97" to="v112"/>
 <arc name="v11->v26" from="v11" to="v26"/>
 <arc name="v42->v57" from="v42" to="v57"/>
 <arc name="v110->v116" from="v110" to="v116"/>
 <arc name="v57->v74" from="v57" to="v74"/>
 <arc name="v38->v41" from="v38" to="v41"/>
 <arc name="v80->v84" from="v80" to="v84"/>
 <arc name="v16->v33" from="v16" to="v33"/>
 <arc name="v78->v90" from="v78" to="v90"/>
 <arc name="v42->v59" from="v42" to="v59"/>
 <arc name="v25->v29" from="v25" to="v29"/>
 <arc name="v17->v35" from="v17" to="v35"/>
 <arc name="v35->v48" from="v35" to="v48"/>
 <arc name="v89->v101" from="v89" to="v101"/>
 <arc name="v63->v71" from="v63" to="v71"/>
 <arc name="v90->v98" from="v90" to="v98"/>
 <arc name="v36->v50" from="v36" to="v50"/>
 <arc name="v78->v86" from="v78" to="v86"/>
 <arc name="v37->v43" from="v37" to="v43"/>
 <arc name="v37->v50" from="v37" to="v50"/>
 <arc name="v57->v67" from="v57" to="v67"/>
 <arc name="v12->v14" from="v12" to="v14"/>
 <arc name="v56->v75" from="v56" to="v75"/>
 <arc name="v04->v19" from="v04" to="v19"/>
 <arc name="v47->v57" from="v47" to="v57"/>
 <arc name="v113->v126" from="v113" to="v126"/>
 <arc name="v77->v90" from="v77" to="v90"/>
 <arc name="v02->v20" from="v02" to="v20"/>
 <arc name="v38->v47" from="v38" to="v47"/>
 <arc name="v84->v103" from="v84" to="v103"/>
 <arc name="v05->v24" from="v05" to="v24"/>
 <arc name="v96->v108" from="v96" to="v108"/>
 <arc name="v90->v96" from="v90" to="v96"/>
 <arc name="v30->v49" from="v30" to="v49"/>
 <arc name="v107->v116" from="v107" to="v116"/>
 <arc name="v91->v97" from="v91" to="v97"/>
 <arc name="v102->v111" from="v102" to="v111"/>
 <arc name="v40->v42" from="v40" to="v42"/>
 <arc name="v05->v27" from="v05" to="v27"/>
 <arc name="v68->v76" from="v68" to="v76"/>
 <arc name="v45->v55" from="v45" to="v55"/>
 <arc name="v14->v39" from="v14" to="v39"/>
 <arc name="v104->v108" from="v104" to="v108"/>
 <arc name="v42->v55" from="v42" to="v55"/>
 <arc name="v61->v67" from="v61" to="v67"/>
 <arc name="v37->v45" from="v37" to="v45"/>
 <arc name="v62->v72" from="v62" to="v72"/>
 <arc name="v80->v86" from="v80" to="v86"/>
 <arc name="v06->v14" from="v06" to="v14"/>
 <arc name="v56->v70" from="v56" to="v70"/>
 <arc name="v06->v22" from="v06" to="v22"/>
 <arc name="v77->v93" from="v77" to="v93"/>
 <arc name="v85->v105" from="v85" to="v105"/>
 <arc name="v62->v71" from="v62" to="v71"/>
 <arc name="v103->v108" from="v103" to="v108"/>
 <arc name="v05->v23" from="v05" to="v23"/>
 <arc name="v117->v129" from="v117" to="v129"/>
 <arc name="v44->v63" from="v44" to="v63"/>
 <arc name="v114->v127" from="v114" to="v127"/>
 <arc name="v102->v108" from="v102" to="v108"/>
 <arc name="v117->v121" from="v117" to="v121"/>
 <arc name="v28->v48" from="v28" to="v48"/>
 <arc name="v16->v28" from="v16" to="v28"/>
 <arc name="v119->v125" from="v119" to="v125"/>
 <arc name="v59->v68" from="v59" to="v68"/>
 <arc name="v61->v68" from="v61" to="v68"/>
 <arc name="v42->v61" from="v42" to="v61"/>
 <arc name="v80->v83" from="v80" to="v83"/>
 <arc name="v43->v53" from="v43" to="v53"/>
 <arc name="v108->v120" from="v108" to="v120"/>
 <arc name="v95->v110" from="v95" to="v110"/>
 <arc name="v101->v111" from="v101" to="v111"/>
 <arc name="v21->v35" from="v21" to="v35"/>
 <arc name="v112->v116" from="v112" to="v116"/>
 <arc name="v73->v77" from="v73" to="v77"/>
 <arc name="v15->v31" from="v15" to="v31"/>
 <arc name="v103->v112" from="v103" to="v112"/>
 <arc name="v06->v23" from="v06" to="v23"/>
 <arc name="v31->v48" from="v31" to="v48"/>
 <arc name="v80->v88" from="v80" to="v88"/>
 <arc name="v18->v36" from="v18" to="v36"/>
 <arc name="v48->v58" from="v48" to="v58"/>
 <arc name="v119->v129" from="v119" to="v129"/>
 <arc name="v00->v27" from="v00" to="v27"/>
 <arc name="v00->v23" from="v00" to="v23"/>
 <arc name="v58->v74" from="v58" to="v74"/>
 <arc name="v87->v105" from="v87" to="v105"/>
 <arc name="v118->v126" from="v118" to="v126"/>
 <arc name="v55->v72" from="v55" to="v72"/>
 <arc name="v118->v123" from="v118" to="v123"/>
 <arc name="v44->v62" from="v44" to="v62"/>
 <arc name="v90->v106" from="v90" to="v106"/>
 <arc name="v89->v103" from="v89" to="v103"/>
 <arc name="v13->v20" from="v13" to="v20"/>
 <arc name="v19->v37" from="v19" to="v37"/>
 <arc name="v23->v39" from="v23" to="v39"/>
 <arc name="v08->v19" from="v08" to="v19"/>
 <arc name="v111->v115" from="v111" to="v115"/>
 <arc name="v52->v68" from="v52" to="v68"/>
 <arc name="v71->v77" from="v71" to="v77"/>
 <arc name="v03->v21" from="v03" to="v21"/>
 <arc name="v58->v65" from="v58" to="v65"/>
 <arc name="v73->v76" from="v73" to="v76"/>
 <arc name="v78->v84" from="v78" to="v84"/>
 <arc name="v118->v125" from="v118" to="v125"/>
 <arc name="v08->v27" from="v08" to="v27"/>
 <arc name="v32->v47" from="v32" to="v47"/>
 <arc name="v64->v77" from="v64" to="v77"/>
 <arc name="v63->v68" from="v63" to="v68"/>
 <arc name="v49->v60" from="v49" to="v60"/>
 <arc name="v75->v77" from="v75" to="v77"/>
 <arc name="v102->v107" from="v102" to="v107"/>
 <arc name="v11->v27" from="v11" to="v27"/>
 <arc name="v39->v42" from="v39" to="v42"/>
 <arc name="v17->v28" from="v17" to="v28"/>
 <arc name="v41->v61" from="v41" to="v61"/>
 <arc name="v109->v113" from="v109" to="v113"/>
 <arc name="v46->v56" from="v46" to="v56"/>
 <arc name="v05->v21" from="v05" to="v21"/>
 <arc name="v89->v106" from="v89" to="v106"/>
 <arc name="v18->v40" from="v18" to="v40"/>
 <arc name="v72->v77" from="v72" to="v77"/>
 <arc name="v110->v114" from="v110" to="v114"/>
 <arc name="v26->v31" from="v26" to="v31"/>
 <arc name="v22->v33" from="v22" to="v33"/>
 <arc name="v32->v46" from="v32" to="v46"/>
 <arc name="v79->v85" from="v79" to="v85"/>
 <arc name="v50->v61" from="v50" to="v61"/>
 <arc name="v111->v114" from="v111" to="v114"/>
 <arc name="v49->v58" from="v49" to="v58"/>
 <arc name="v61->v74" from="v61" to="v74"/>
 <arc name="v111->v116" from="v111" to="v116"/>
 <arc name="v32->v42" from="v32" to="v42"/>
 <arc name="v109->v117" from="v109" to="v117"/>
 <arc name="v21->v31" from="v21" to="v31"/>
 <arc name="v82->v100" from="v82" to="v100"/>
 <arc name="v38->v50" from="v38" to="v50"/>
 <arc name="v108->v119" from="v108" to="v119"/>
 <arc name="v114->v124" from="v114" to="v124"/>
 <arc name="v101->v112" from="v101" to="v112"/>
 <arc name="v16->v39" from="v16" to="v39"/>
 <arc name="v85->v99" from="v85" to="v99"/>
 <arc name="v23->v33" from="v23" to="v33"/>
 <arc name="v91->v106" from="v91" to="v106"/>
 <arc name="v70->v77" from="v70" to="v77"/>
 <arc name="v120->v125" from="v120" to="v125"/>
 <arc name="v19->v33" from="v19" to="v33"/>
 <arc name="v34->v44" from="v34" to="v44"/>
 <arc name="v06->v27" from="v06" to="v27"/>
 <arc name="v34->v48" from="v34" to="v48"/>
 <arc name="v10->v18" from="v10" to="v18"/>
 <arc name="v101->v109" from="v101" to="v109"/>
 <arc name="v41->v59" from="v41" to="v59"/>
 <arc name="v07->v22" from="v07" to="v22"/>
 <arc name="v105->v110" from="v105" to="v110"/>
 <arc name="v67->v78" from="v67" to="v78"/>
 <arc name="v51->v65" from="v51" to="v65"/>
 <arc name="v83->v104" from="v83" to="v104"/>
 <arc name="v117->v127" from="v117" to="v127"/>
 <arc name="v78->v91" from="v78" to="v91"/>
 <arc name="v42->v60" from="v42" to="v60"/>
 <arc name="v08->v16" from="v08" to="v16"/>
 <arc name="v26->v40" from="v26" to="v40"/>
 <arc name="v65->v80" from="v65" to="v80"/>
 <arc name="v77->v89" from="v77" to="v89"/>
 <arc name="v90->v105" from="v90" to="v105"/>
 <arc name="v39->v41" from="v39" to="v41"/>
 <arc name="v87->v103" from="v87" to="v103"/>
 <arc name="v113->v125" from="v113" to="v125"/>
 <arc name="v100->v112" from="v100" to="v112"/>
 <arc name="v57->v65" from="v57" to="v65"/>
 <arc name="v16->v30" from="v16" to="v30"/>
 <arc name="v80->v82" from="v80" to="v82"/>
 <arc name="v05->v20" from="v05" to="v20"/>
 <arc name="v88->v106" from="v88" to="v106"/>
 <arc name="v32->v50" from="v32" to="v50"/>
 <arc name="v02->v23" from="v02" to="v23"/>
 <arc name="v111->v120" from="v111" to="v120"/>
 <arc name="v19->v39" from="v19" to="v39"/>
 <arc name="v81->v106" from="v81" to="v106"/>
 <arc name="v37->v44" from="v37" to="v44"/>
 <arc name="v119->v123" from="v119" to="v123"/>
 <arc name="v19->v34" from="v19" to="v34"/>
 <arc name="v18->v35" from="v18" to="v35"/>
 <arc name="v56->v65" from="v56" to="v65"/>
 <arc name="v51->v70" from="v51" to="v70"/>
 <arc name="v36->v41" from="v36" to="v41"/>
 <arc name="v69->v76" from="v69" to="v76"/>
 <arc name="v92->v104" from="v92" to="v104"/>
 <arc name="v29->v46" from="v29" to="v46"/>
 <arc name="v81->v99" from="v81" to="v99"/>
 <arc name="v23->v40" from="v23" to="v40"/>
 <arc name="v32->v48" from="v32" to="v48"/>
 <arc name="v110->v119" from="v110" to="v119"/>
 <arc name="v104->v107" from="v104" to="v107"/>
 <arc name="v96->v110" from="v96" to="v110"/>
 <arc name="v110->v115" from="v110" to="v115"/>
 <arc name="v78->v82" from="v78" to="v82"/>
 <arc name="v114->v122" from="v114" to="v122"/>
 <arc name="v07->v14" from="v07" to="v14"/>
 <arc name="v13->v22" from="v13" to="v22"/>
 <arc name="v80->v91" from="v80" to="v91"/>
 <arc name="v43->v55" from="v43" to="v55"/>
 <arc name="v120->v122" from="v120" to="v122"/>
 <arc name="v54->v73" from="v54" to="v73"/>
 <arc name="v104->v109" from="v104" to="v109"/>
 <arc name="v56->v71" from="v56" to="v71"/>
 <arc name="v12->v21" from="v12" to="v21"/>
 <arc name="v79->v82" from="v79" to="v82"/>
 <arc name="v03->v19" from="v03" to="v19"/>
 <arc name="v15->v33" from="v15" to="v33"/>
 <arc name="v114->v125" from="v114" to="v125"/>
 <arc name="v26->v38" from="v26" to="v38"/>
 <arc name="v87->v106" from="v87" to="v106"/>
 <arc name="v54->v69" from="v54" to="v69"/>
 <arc name="v91->v103" from="v91" to="v103"/>
 <arc name="v89->v97" from="v89" to="v97"/>
 <arc name="v50->v58" from="v50" to="v58"/>
 <arc name="v117->v122" from="v117" to="v122"/>
 <arc name="v76->v85" from="v76" to="v85"/>
 <arc name="v35->v47" from="v35" to="v47"/>
 <arc name="v107->v119" from="v107" to="v119"/>
 <arc name="v60->v65" from="v60" to="v65"/>
 <arc name="v63->v69" from="v63" to="v69"/>
 <arc name="v17->v34" from="v17" to="v34"/>
 <arc name="v110->v113" from="v110" to="v113"/>
 <arc name="v107->v120" from="v107" to="v120"/>
 <arc name="v50->v53" from="v50" to="v53"/>
 <arc name="v87->v99" from="v87" to="v99"/>
 <arc name="v97->v107" from="v97" to="v107"/>
 <arc name="v97->v109" from="v97" to="v109"/>
 <arc name="v113->v128" from="v113" to="v128"/>
 <arc name="v120->v123" from="v120" to="v123"/>
 <arc name="v27->v37" from="v27" to="v37"/>
 <arc name="v80->v81" from="v80" to="v81"/>
 <arc name="v02->v19" from="v02" to="v19"/>
 <arc name="v57->v68" from="v57" to="v68"/>
 <arc name="v01->v19" from="v01" to="v19"/>
 <arc name="v78->v93" from="v78" to="v93"/>
 <arc name="v05->v26" from="v05" to="v26"/>
 <arc name="v25->v32" from="v25" to="v32"/>
 <arc name="v79->v86" from="v79" to="v86"/>
 <arc name="v39->v47" from="v39" to="v47"/>
 <arc name="v54->v67" from="v54" to="v67"/>
 <arc name="v03->v25" from="v03" to="v25"/>
 <arc name="v17->v38" from="v17" to="v38"/>
 <arc name="v52->v66" from="v52" to="v66"/>
 <arc name="v32->v41" from="v32" to="v41"/>
 <arc name="v87->v96" from="v87" to="v96"/>
 <arc name="v117->v128" from="v117" to="v128"/>
 <arc name="v66->v79" from="v66" to="v79"/>
 <arc name="v52->v74" from="v52" to="v74"/>
 <arc name="v06->v19" from="v06" to="v19"/>
 <arc name="v30->v47" from="v30" to="v47"/>
 <arc name="v40->v49" from="v40" to="v49"/>
 <arc name="v77->v83" from="v77" to="v83"/>
 <arc name="v02->v15" from="v02" to="v15"/>
 <arc name="v01->v21" from="v01" to="v21"/>
 <arc name="v45->v62" from="v45" to="v62"/>
 <arc name="v61->v70" from="v61" to="v70"/>
 <arc name="v29->v43" from="v29" to="v43"/>
 <arc name="v115->v128" from="v115" to="v128"/>
 <arc name="v78->v81" from="v78" to="v81"/>
 <arc name="v100->v111" from="v100" to="v111"/>
 <arc name="v46->v63" from="v46" to="v63"/>
 <arc name="v76->v90" from="v76" to="v90"/>
 <arc name="v41->v58" from="v41" to="v58"/>
 <arc name="v88->v98" from="v88" to="v98"/>
 <arc name="v87->v102" from="v87" to="v102"/>
 <arc name="v82->v98" from="v82" to="v98"/>
 <arc name="v33->v42" from="v33" to="v42"/>
 <arc name="v55->v75" from="v55" to="v75"/>
 <arc name="v94->v111" from="v94" to="v111"/>
 <arc name="v30->v41" from="v30" to="v41"/>
 <arc name="v119->v126" from="v119" to="v126"/>
 <arc name="v102->v112" from="v102" to="v112"/>
 <arc name="v117->v125" from="v117" to="v125"/>
 <arc name="v113->v123" from="v113" to="v123"/>
 <arc name="v74->v76" from="v74" to="v76"/>
 <arc name="v84->v99" from="v84" to="v99"/>
 <arc name="v26->v37" from="v26" to="v37"/>
 <arc name="v09->v14" from="v09" to="v14"/>
 <arc name="v54->v72" from="v54" to="v72"/>
 <arc name="v76->v86" from="v76" to="v86"/>
 <arc name="v49->v52" from="v49" to="v52"/>
 <arc name="v94->v108" from="v94" to="v108"/>
 <arc name="v95->v112" from="v95" to="v112"/>
 <arc name="v39->v48" from="v39" to="v48"/>
 <arc name="v11->v15" from="v11" to="v15"/>
 <arc name="v120->v126" from="v120" to="v126"/>
 <arc name="v51->v71" from="v51" to="v71"/>
 <arc name="v116->v126" from="v116" to="v126"/>
 <arc name="v03->v18" from="v03" to="v18"/>
 <arc name="v77->v82" from="v77" to="v82"/>
 <arc name="v43->v59" from="v43" to="v59"/>
 <arc name="v07->v24" from="v07" to="v24"/>
 <arc name="v07->v16" from="v07" to="v16"/>
 <arc name="v31->v42" from="v31" to="v42"/>
 <arc name="v27->v35" from="v27" to="v35"/>
 <arc name="v62->v66" from="v62" to="v66"/>
 <arc name="v45->v56" from="v45" to="v56"/>
 <arc name="v54->v65" from="v54" to="v65"/>
 <arc name="v27->v32" from="v27" to="v32"/>
 <arc name="v92->v103" from="v92" to="v103"/>
 <arc name="v115->v123" from="v115" to="v123"/>
 <arc name="v33->v49" from="v33" to="v49"/>
 <arc name="v17->v37" from="v17" to="v37"/>
 <arc name="v70->v80" from="v70" to="v80"/>
 <arc name="v64->v78" from="v64" to="v78"/>
 <arc name="v40->v41" from="v40" to="v41"/>
 <arc name="v59->v65" from="v59" to="v65"/>
 <arc name="v63->v64" from="v63" to="v64"/>
 <arc name="v53->v75" from="v53" to="v75"/>
 <arc name="v76->v88" from="v76" to="v88"/>
 <arc name="v46->v60" from="v46" to="v60"/>
 <arc name="v118->v124" from="v118" to="v124"/>
 <arc name="v79->v88" from="v79" to="v88"/>
 <arc name="v13->v14" from="v13" to="v14"/>
 <arc name="v08->v17" from="v08" to="v17"/>
 <arc name="v06->v17" from="v06" to="v17"/>
 <arc name="v86->v100" from="v86" to="v100"/>
 <arc name="v18->v29" from="v18" to="v29"/>
 <arc name="v76->v93" from="v76" to="v93"/>
 <arc name="v29->v45" from="v29" to="v45"/>
 <arc name="v102->v109" from="v102" to="v109"/>
 <arc name="v57->v64" from="v57" to="v64"/>
 <arc name="v85->v101" from="v85" to="v101"/>
 <arc name="v10->v15" from="v10" to="v15"/>
 <arc name="v51->v73" from="v51" to="v73"/>
 <arc name="v86->v96" from="v86" to="v96"/>
</graph>
